wpmusic/__init__.py
wpmusic/audio_track.py
wpmusic/configs/__init__.py
wpmusic/configs/table_config.py
wpmusic/configs/wp_config.py
wpmusic/db_manager.py
wpmusic/file_manager.py
wpmusic/main.py
wpmusic/metadata_fetcher.py
wpmusic/metadata_setter.py
wpmusic/scripts/__init__.py
wpmusic/scripts/db_migrator.py
wpmusic/track_identifier.py
wpmusic/upload_tracker.py
wpmusic-0.1.2.dist-info/METADATA
wpmusic-0.1.2.dist-info/WHEEL
wpmusic-0.1.2.dist-info/entry_points.txt
wpmusic-0.1.2.dist-info/RECORD
